lets_plot_kotlin_bridge.cpython-314-x86_64-linux-gnu.so
lets_plot/__init__.py
lets_plot/_global_settings.py
lets_plot/_kbridge.py
lets_plot/_type_utils.py
lets_plot/_version.py
lets_plot/mapping.py
lets_plot/settings_utils.py
lets_plot/tilesets.py
lets_plot/bistro/__init__.py
lets_plot/bistro/_plot2d_common.py
lets_plot/bistro/corr.py
lets_plot/bistro/im.py
lets_plot/bistro/joint.py
lets_plot/bistro/qq.py
lets_plot/bistro/residual.py
lets_plot/bistro/waterfall.py
lets_plot/export/__init__.py
lets_plot/export/ggsave_.py
lets_plot/frontend_context/__init__.py
lets_plot/frontend_context/_configuration.py
lets_plot/frontend_context/_dynamic_configure_html.py
lets_plot/frontend_context/_frontend_ctx.py
lets_plot/frontend_context/_html_contexts.py
lets_plot/frontend_context/_intellij_python_json_ctx.py
lets_plot/frontend_context/_isolated_webview_panel_ctx.py
lets_plot/frontend_context/_json_contexts.py
lets_plot/frontend_context/_jupyter_notebook_ctx.py
lets_plot/frontend_context/_mime_types.py
lets_plot/frontend_context/_static_html_page_ctx.py
lets_plot/frontend_context/_static_svg_ctx.py
lets_plot/frontend_context/_webbr_html_page_ctx.py
lets_plot/frontend_context/sandbox.py
lets_plot/geo_data/__init__.py
lets_plot/geo_data/core.py
lets_plot/geo_data/geocoder.py
lets_plot/geo_data/geocodes.py
lets_plot/geo_data/livemap_helper.py
lets_plot/geo_data/to_geo_data_frame.py
lets_plot/geo_data/type_assertion.py
lets_plot/geo_data/gis/__init__.py
lets_plot/geo_data/gis/fluent_dict.py
lets_plot/geo_data/gis/geocoding_service.py
lets_plot/geo_data/gis/geometry.py
lets_plot/geo_data/gis/json_request.py
lets_plot/geo_data/gis/json_response.py
lets_plot/geo_data/gis/request.py
lets_plot/geo_data/gis/response.py
lets_plot/geo_data_internals/__init__.py
lets_plot/geo_data_internals/constants.py
lets_plot/geo_data_internals/utils.py
lets_plot/package_data/lets-plot.min.js
lets_plot/plot/__init__.py
lets_plot/plot/_global_theme.py
lets_plot-4.8.2.dist-info/METADATA
lets_plot-4.8.2.dist-info/WHEEL
lets_plot-4.8.2.dist-info/top_level.txt
lets_plot-4.8.2.dist-info/RECORD
lets_plot-4.8.2.dist-info/licenses/LICENSE
lets_plot-4.8.2.dist-info/licenses/licenses/LICENSE.FreeType
lets_plot-4.8.2.dist-info/licenses/licenses/LICENSE.ImageMagick
lets_plot-4.8.2.dist-info/licenses/licenses/LICENSE.expat
lets_plot-4.8.2.dist-info/licenses/licenses/LICENSE.fontconfig
