Metadata-Version: 2.4
Name: lets-plot
Version: 4.8.2
Summary: An open source library for statistical plotting
Home-page: https://lets-plot.org
Author: JetBrains
Author-email: lets-plot@jetbrains.com
Maintainer: JetBrains
Maintainer-email: lets-plot@jetbrains.com
License: MIT
Project-URL: Github, https://github.com/JetBrains/lets-plot
Project-URL: Documentation, https://lets-plot.org
Keywords: ggplot,ggplot2,geospatial,geopandas,geocoding
Classifier: Development Status :: 5 - Production/Stable
Classifier: Programming Language :: Python :: 3.9
Classifier: Programming Language :: Python :: 3.10
Classifier: Programming Language :: Python :: 3.11
Classifier: Programming Language :: Python :: 3.12
Classifier: Programming Language :: Python :: 3.13
Classifier: Framework :: IPython
Classifier: Framework :: Jupyter
Classifier: Operating System :: MacOS
Classifier: Operating System :: POSIX :: Linux
Classifier: Operating System :: Microsoft :: Windows
Classifier: Programming Language :: Python :: Implementation :: CPython
Classifier: Topic :: Scientific/Engineering :: Visualization
Classifier: Intended Audience :: Science/Research
Classifier: Intended Audience :: Developers
License-File: LICENSE
License-File: licenses/LICENSE.FreeType
License-File: licenses/LICENSE.ImageMagick
License-File: licenses/LICENSE.expat
License-File: licenses/LICENSE.fontconfig
Requires-Dist: pypng
Requires-Dist: palettable
Requires-Dist: pillow
Dynamic: author
Dynamic: author-email
Dynamic: classifier
Dynamic: description
Dynamic: description-content-type
Dynamic: home-page
Dynamic: keywords
Dynamic: license
Dynamic: license-file
Dynamic: maintainer
Dynamic: maintainer-email
Dynamic: project-url
Dynamic: requires-dist
Dynamic: summary
